{
  "scriptId": "743",
  "url": "file:///C:/Users/luisf/AppData/Local/deno/npm/registry.npmjs.org/mongodb/6.5.0/lib/cmap/connection.js",
  "functions": [
    {
      "functionName": "",
      "ranges": [
        {
          "startOffset": 0,
          "endOffset": 20382,
          "count": 1
        }
      ],
      "isBlockCoverage": true
    },
    {
      "functionName": "",
      "ranges": [
        {
          "startOffset": 1,
          "endOffset": 20381,
          "count": 1
        }
      ],
      "isBlockCoverage": true
    },
    {
      "functionName": "",
      "ranges": [
        {
          "startOffset": 214,
          "endOffset": 20375,
          "count": 1
        }
      ],
      "isBlockCoverage": true
    },
    {
      "functionName": "hasSessionSupport",
      "ranges": [
        {
          "startOffset": 1214,
          "endOffset": 1353,
          "count": 0
        }
      ],
      "isBlockCoverage": false
    },
    {
      "functionName": "streamIdentifier",
      "ranges": [
        {
          "startOffset": 1401,
          "endOffset": 1953,
          "count": 0
        }
      ],
      "isBlockCoverage": false
    },
    {
      "functionName": "Connection",
      "ranges": [
        {
          "startOffset": 2034,
          "endOffset": 3280,
          "count": 0
        }
      ],
      "isBlockCoverage": false
    },
    {
      "functionName": "get hello",
      "ranges": [
        {
          "startOffset": 3285,
          "endOffset": 3343,
          "count": 0
        }
      ],
      "isBlockCoverage": false
    },
    {
      "functionName": "set hello",
      "ranges": [
        {
          "startOffset": 3435,
          "endOffset": 3555,
          "count": 0
        }
      ],
      "isBlockCoverage": false
    },
    {
      "functionName": "get serviceId",
      "ranges": [
        {
          "startOffset": 3560,
          "endOffset": 3621,
          "count": 0
        }
      ],
      "isBlockCoverage": false
    },
    {
      "functionName": "get loadBalanced",
      "ranges": [
        {
          "startOffset": 3626,
          "endOffset": 3698,
          "count": 0
        }
      ],
      "isBlockCoverage": false
    },
    {
      "functionName": "get idleTime",
      "ranges": [
        {
          "startOffset": 3703,
          "endOffset": 3794,
          "count": 0
        }
      ],
      "isBlockCoverage": false
    },
    {
      "functionName": "get hasSessionSupport",
      "ranges": [
        {
          "startOffset": 3799,
          "endOffset": 3900,
          "count": 0
        }
      ],
      "isBlockCoverage": false
    },
    {
      "functionName": "get supportsOpMsg",
      "ranges": [
        {
          "startOffset": 3905,
          "endOffset": 4085,
          "count": 0
        }
      ],
      "isBlockCoverage": false
    },
    {
      "functionName": "get shouldEmitAndLogCommand",
      "ranges": [
        {
          "startOffset": 4090,
          "endOffset": 4406,
          "count": 0
        }
      ],
      "isBlockCoverage": false
    },
    {
      "functionName": "markAvailable",
      "ranges": [
        {
          "startOffset": 4411,
          "endOffset": 4481,
          "count": 0
        }
      ],
      "isBlockCoverage": false
    },
    {
      "functionName": "onError",
      "ranges": [
        {
          "startOffset": 4486,
          "endOffset": 4537,
          "count": 0
        }
      ],
      "isBlockCoverage": false
    },
    {
      "functionName": "onClose",
      "ranges": [
        {
          "startOffset": 4542,
          "endOffset": 4696,
          "count": 0
        }
      ],
      "isBlockCoverage": false
    },
    {
      "functionName": "onTimeout",
      "ranges": [
        {
          "startOffset": 4701,
          "endOffset": 5094,
          "count": 0
        }
      ],
      "isBlockCoverage": false
    },
    {
      "functionName": "destroy",
      "ranges": [
        {
          "startOffset": 5099,
          "endOffset": 5608,
          "count": 0
        }
      ],
      "isBlockCoverage": false
    },
    {
      "functionName": "cleanup",
      "ranges": [
        {
          "startOffset": 5919,
          "endOffset": 6219,
          "count": 0
        }
      ],
      "isBlockCoverage": false
    },
    {
      "functionName": "prepareCommand",
      "ranges": [
        {
          "startOffset": 6224,
          "endOffset": 9722,
          "count": 0
        }
      ],
      "isBlockCoverage": false
    },
    {
      "functionName": "sendWire",
      "ranges": [
        {
          "startOffset": 9727,
          "endOffset": 11557,
          "count": 0
        }
      ],
      "isBlockCoverage": false
    },
    {
      "functionName": "sendCommand",
      "ranges": [
        {
          "startOffset": 11562,
          "endOffset": 13857,
          "count": 0
        }
      ],
      "isBlockCoverage": false
    },
    {
      "functionName": "command",
      "ranges": [
        {
          "startOffset": 13862,
          "endOffset": 14159,
          "count": 0
        }
      ],
      "isBlockCoverage": false
    },
    {
      "functionName": "exhaustCommand",
      "ranges": [
        {
          "startOffset": 14164,
          "endOffset": 14643,
          "count": 0
        }
      ],
      "isBlockCoverage": false
    },
    {
      "functionName": "throwIfAborted",
      "ranges": [
        {
          "startOffset": 14648,
          "endOffset": 14726,
          "count": 0
        }
      ],
      "isBlockCoverage": false
    },
    {
      "functionName": "writeCommand",
      "ranges": [
        {
          "startOffset": 14974,
          "endOffset": 15560,
          "count": 0
        }
      ],
      "isBlockCoverage": false
    },
    {
      "functionName": "readMany",
      "ranges": [
        {
          "startOffset": 15977,
          "endOffset": 16480,
          "count": 0
        }
      ],
      "isBlockCoverage": false
    },
    {
      "functionName": "SizedMessageTransform",
      "ranges": [
        {
          "startOffset": 17060,
          "endOffset": 17223,
          "count": 0
        }
      ],
      "isBlockCoverage": false
    },
    {
      "functionName": "_transform",
      "ranges": [
        {
          "startOffset": 17228,
          "endOffset": 17991,
          "count": 0
        }
      ],
      "isBlockCoverage": false
    },
    {
      "functionName": "CryptoConnection",
      "ranges": [
        {
          "startOffset": 18114,
          "endOffset": 18234,
          "count": 0
        }
      ],
      "isBlockCoverage": false
    },
    {
      "functionName": "command",
      "ranges": [
        {
          "startOffset": 18270,
          "endOffset": 20287,
          "count": 0
        }
      ],
      "isBlockCoverage": false
    }
  ]
}