{
  "scriptId": "884",
  "url": "file:///C:/Users/AGX/AppData/Local/deno/npm/registry.npmjs.org/mongoose/8.19.1/lib/stateMachine.js",
  "functions": [
    {
      "functionName": "",
      "ranges": [
        {
          "startOffset": 0,
          "endOffset": 5822,
          "count": 1
        }
      ],
      "isBlockCoverage": true
    },
    {
      "functionName": "",
      "ranges": [
        {
          "startOffset": 1,
          "endOffset": 5821,
          "count": 1
        }
      ],
      "isBlockCoverage": true
    },
    {
      "functionName": "",
      "ranges": [
        {
          "startOffset": 214,
          "endOffset": 5815,
          "count": 1
        }
      ],
      "isBlockCoverage": true
    },
    {
      "functionName": "StateMachine",
      "ranges": [
        {
          "startOffset": 530,
          "endOffset": 557,
          "count": 1
        }
      ],
      "isBlockCoverage": true
    },
    {
      "functionName": "StateMachine.ctor",
      "ranges": [
        {
          "startOffset": 1018,
          "endOffset": 1493,
          "count": 1
        }
      ],
      "isBlockCoverage": true
    },
    {
      "functionName": "ctor",
      "ranges": [
        {
          "startOffset": 1080,
          "endOffset": 1180,
          "count": 0
        }
      ],
      "isBlockCoverage": false
    },
    {
      "functionName": "",
      "ranges": [
        {
          "startOffset": 1316,
          "endOffset": 1473,
          "count": 5
        }
      ],
      "isBlockCoverage": true
    },
    {
      "functionName": "ctor.<computed>",
      "ranges": [
        {
          "startOffset": 1408,
          "endOffset": 1468,
          "count": 0
        }
      ],
      "isBlockCoverage": false
    },
    {
      "functionName": "_changeState",
      "ranges": [
        {
          "startOffset": 1683,
          "endOffset": 2029,
          "count": 0
        }
      ],
      "isBlockCoverage": false
    },
    {
      "functionName": "clear",
      "ranges": [
        {
          "startOffset": 2082,
          "endOffset": 2349,
          "count": 0
        }
      ],
      "isBlockCoverage": false
    },
    {
      "functionName": "clearPath",
      "ranges": [
        {
          "startOffset": 2406,
          "endOffset": 2562,
          "count": 0
        }
      ],
      "isBlockCoverage": false
    },
    {
      "functionName": "getStatePaths",
      "ranges": [
        {
          "startOffset": 2698,
          "endOffset": 2815,
          "count": 0
        }
      ],
      "isBlockCoverage": false
    },
    {
      "functionName": "some",
      "ranges": [
        {
          "startOffset": 3050,
          "endOffset": 3336,
          "count": 0
        }
      ],
      "isBlockCoverage": false
    },
    {
      "functionName": "_iter",
      "ranges": [
        {
          "startOffset": 3621,
          "endOffset": 4128,
          "count": 0
        }
      ],
      "isBlockCoverage": false
    },
    {
      "functionName": "forEach",
      "ranges": [
        {
          "startOffset": 4625,
          "endOffset": 4733,
          "count": 0
        }
      ],
      "isBlockCoverage": false
    },
    {
      "functionName": "map",
      "ranges": [
        {
          "startOffset": 5241,
          "endOffset": 5333,
          "count": 0
        }
      ],
      "isBlockCoverage": false
    },
    {
      "functionName": "clone",
      "ranges": [
        {
          "startOffset": 5491,
          "endOffset": 5811,
          "count": 0
        }
      ],
      "isBlockCoverage": false
    }
  ]
}