{
  "scriptId": "464",
  "url": "file:///C:/Users/luisf/AppData/Local/deno/npm/registry.npmjs.org/axios/1.12.2/lib/helpers/estimateDataURLDecodedBytes.js",
  "functions": [
    {
      "functionName": "",
      "ranges": [
        {
          "startOffset": 0,
          "endOffset": 2060,
          "count": 1
        }
      ],
      "isBlockCoverage": true
    },
    {
      "functionName": "estimateDataURLDecodedBytes",
      "ranges": [
        {
          "startOffset": 391,
          "endOffset": 2059,
          "count": 0
        }
      ],
      "isBlockCoverage": false
    }
  ]
}