{
  "scriptId": "472",
  "url": "file:///C:/Users/AGX/AppData/Local/deno/npm/registry.npmjs.org/date-fns/4.1.0/getISOWeekYear.js",
  "functions": [
    {
      "functionName": "",
      "ranges": [
        {
          "startOffset": 0,
          "endOffset": 1629,
          "count": 1
        }
      ],
      "isBlockCoverage": true
    },
    {
      "functionName": "getISOWeekYear",
      "ranges": [
        {
          "startOffset": 776,
          "endOffset": 1559,
          "count": 0
        }
      ],
      "isBlockCoverage": false
    }
  ]
}