{
  "scriptId": "753",
  "url": "file:///C:/Users/luisf/AppData/Local/deno/npm/registry.npmjs.org/mongodb/6.5.0/lib/cmap/auth/mongocr.js",
  "functions": [
    {
      "functionName": "",
      "ranges": [
        {
          "startOffset": 0,
          "endOffset": 1594,
          "count": 1
        }
      ],
      "isBlockCoverage": true
    },
    {
      "functionName": "",
      "ranges": [
        {
          "startOffset": 1,
          "endOffset": 1593,
          "count": 1
        }
      ],
      "isBlockCoverage": true
    },
    {
      "functionName": "",
      "ranges": [
        {
          "startOffset": 214,
          "endOffset": 1587,
          "count": 1
        }
      ],
      "isBlockCoverage": true
    },
    {
      "functionName": "auth",
      "ranges": [
        {
          "startOffset": 547,
          "endOffset": 1520,
          "count": 0
        }
      ],
      "isBlockCoverage": false
    }
  ]
}