{
  "scriptId": "653",
  "url": "file:///C:/Users/luisf/AppData/Local/deno/npm/registry.npmjs.org/mongodb/6.5.0/lib/cmap/commands.js",
  "functions": [
    {
      "functionName": "",
      "ranges": [
        {
          "startOffset": 0,
          "endOffset": 22724,
          "count": 1
        }
      ],
      "isBlockCoverage": true
    },
    {
      "functionName": "",
      "ranges": [
        {
          "startOffset": 1,
          "endOffset": 22723,
          "count": 1
        }
      ],
      "isBlockCoverage": true
    },
    {
      "functionName": "",
      "ranges": [
        {
          "startOffset": 214,
          "endOffset": 22717,
          "count": 1
        }
      ],
      "isBlockCoverage": true
    },
    {
      "functionName": "OpQueryRequest",
      "ranges": [
        {
          "startOffset": 1195,
          "endOffset": 3341,
          "count": 0
        }
      ],
      "isBlockCoverage": false
    },
    {
      "functionName": "incRequestId",
      "ranges": [
        {
          "startOffset": 3381,
          "endOffset": 3442,
          "count": 0
        }
      ],
      "isBlockCoverage": false
    },
    {
      "functionName": "nextRequestId",
      "ranges": [
        {
          "startOffset": 3480,
          "endOffset": 3534,
          "count": 0
        }
      ],
      "isBlockCoverage": false
    },
    {
      "functionName": "getRequestId",
      "ranges": [
        {
          "startOffset": 3596,
          "endOffset": 3647,
          "count": 0
        }
      ],
      "isBlockCoverage": false
    },
    {
      "functionName": "toBin",
      "ranges": [
        {
          "startOffset": 3744,
          "endOffset": 8038,
          "count": 0
        }
      ],
      "isBlockCoverage": false
    },
    {
      "functionName": "OpQueryResponse",
      "ranges": [
        {
          "startOffset": 8127,
          "endOffset": 9434,
          "count": 0
        }
      ],
      "isBlockCoverage": false
    },
    {
      "functionName": "isParsed",
      "ranges": [
        {
          "startOffset": 9439,
          "endOffset": 9485,
          "count": 0
        }
      ],
      "isBlockCoverage": false
    },
    {
      "functionName": "parse",
      "ranges": [
        {
          "startOffset": 9490,
          "endOffset": 12420,
          "count": 0
        }
      ],
      "isBlockCoverage": false
    },
    {
      "functionName": "OpMsgRequest",
      "ranges": [
        {
          "startOffset": 13285,
          "endOffset": 14560,
          "count": 0
        }
      ],
      "isBlockCoverage": false
    },
    {
      "functionName": "toBin",
      "ranges": [
        {
          "startOffset": 14565,
          "endOffset": 15463,
          "count": 0
        }
      ],
      "isBlockCoverage": false
    },
    {
      "functionName": "makeDocumentSegment",
      "ranges": [
        {
          "startOffset": 15468,
          "endOffset": 15804,
          "count": 0
        }
      ],
      "isBlockCoverage": false
    },
    {
      "functionName": "serializeBson",
      "ranges": [
        {
          "startOffset": 15809,
          "endOffset": 16040,
          "count": 0
        }
      ],
      "isBlockCoverage": false
    },
    {
      "functionName": "getRequestId",
      "ranges": [
        {
          "startOffset": 16052,
          "endOffset": 16153,
          "count": 0
        }
      ],
      "isBlockCoverage": false
    },
    {
      "functionName": "OpMsgResponse",
      "ranges": [
        {
          "startOffset": 16236,
          "endOffset": 17747,
          "count": 0
        }
      ],
      "isBlockCoverage": false
    },
    {
      "functionName": "isParsed",
      "ranges": [
        {
          "startOffset": 17752,
          "endOffset": 17798,
          "count": 0
        }
      ],
      "isBlockCoverage": false
    },
    {
      "functionName": "parse",
      "ranges": [
        {
          "startOffset": 17803,
          "endOffset": 20056,
          "count": 0
        }
      ],
      "isBlockCoverage": false
    },
    {
      "functionName": "parseBsonSerializationOptions",
      "ranges": [
        {
          "startOffset": 20061,
          "endOffset": 20265,
          "count": 0
        }
      ],
      "isBlockCoverage": false
    },
    {
      "functionName": "OpCompressedRequest",
      "ranges": [
        {
          "startOffset": 20554,
          "endOffset": 20655,
          "count": 0
        }
      ],
      "isBlockCoverage": false
    },
    {
      "functionName": "canCompress",
      "ranges": [
        {
          "startOffset": 20815,
          "endOffset": 21064,
          "count": 0
        }
      ],
      "isBlockCoverage": false
    },
    {
      "functionName": "toBin",
      "ranges": [
        {
          "startOffset": 21069,
          "endOffset": 22625,
          "count": 0
        }
      ],
      "isBlockCoverage": false
    }
  ]
}