{
  "scriptId": "518",
  "url": "file:///C:/Users/AGX/AppData/Local/deno/npm/registry.npmjs.org/get-proto/1.0.1/Reflect.getPrototypeOf.js",
  "functions": [
    {
      "functionName": "",
      "ranges": [
        {
          "startOffset": 0,
          "endOffset": 380,
          "count": 1
        }
      ],
      "isBlockCoverage": true
    },
    {
      "functionName": "",
      "ranges": [
        {
          "startOffset": 1,
          "endOffset": 379,
          "count": 1
        }
      ],
      "isBlockCoverage": true
    },
    {
      "functionName": "",
      "ranges": [
        {
          "startOffset": 214,
          "endOffset": 373,
          "count": 1
        },
        {
          "startOffset": 362,
          "endOffset": 369,
          "count": 0
        }
      ],
      "isBlockCoverage": true
    }
  ]
}