{
  "scriptId": "913",
  "url": "file:///C:/Users/luisf/AppData/Local/deno/npm/registry.npmjs.org/mongoose/8.3.2/lib/cursor/aggregationCursor.js",
  "functions": [
    {
      "functionName": "",
      "ranges": [
        {
          "startOffset": 0,
          "endOffset": 11012,
          "count": 1
        }
      ],
      "isBlockCoverage": true
    },
    {
      "functionName": "",
      "ranges": [
        {
          "startOffset": 1,
          "endOffset": 11011,
          "count": 1
        }
      ],
      "isBlockCoverage": true
    },
    {
      "functionName": "",
      "ranges": [
        {
          "startOffset": 214,
          "endOffset": 11005,
          "count": 1
        }
      ],
      "isBlockCoverage": true
    },
    {
      "functionName": "AggregationCursor",
      "ranges": [
        {
          "startOffset": 1508,
          "endOffset": 1951,
          "count": 0
        }
      ],
      "isBlockCoverage": false
    },
    {
      "functionName": "_init",
      "ranges": [
        {
          "startOffset": 2017,
          "endOffset": 2795,
          "count": 0
        }
      ],
      "isBlockCoverage": false
    },
    {
      "functionName": "AggregationCursor._read",
      "ranges": [
        {
          "startOffset": 2960,
          "endOffset": 3313,
          "count": 0
        }
      ],
      "isBlockCoverage": false
    },
    {
      "functionName": "AggregationCursor.<computed>",
      "ranges": [
        {
          "startOffset": 3572,
          "endOffset": 3622,
          "count": 0
        }
      ],
      "isBlockCoverage": false
    },
    {
      "functionName": "value",
      "ranges": [
        {
          "startOffset": 4541,
          "endOffset": 4607,
          "count": 0
        }
      ],
      "isBlockCoverage": false
    },
    {
      "functionName": "AggregationCursor._markError",
      "ranges": [
        {
          "startOffset": 4837,
          "endOffset": 4894,
          "count": 0
        }
      ],
      "isBlockCoverage": false
    },
    {
      "functionName": "close",
      "ranges": [
        {
          "startOffset": 5263,
          "endOffset": 5605,
          "count": 0
        }
      ],
      "isBlockCoverage": false
    },
    {
      "functionName": "next",
      "ranges": [
        {
          "startOffset": 5806,
          "endOffset": 6146,
          "count": 0
        }
      ],
      "isBlockCoverage": false
    },
    {
      "functionName": "AggregationCursor.eachAsync",
      "ranges": [
        {
          "startOffset": 6993,
          "endOffset": 7336,
          "count": 0
        }
      ],
      "isBlockCoverage": false
    },
    {
      "functionName": "AggregationCursor.<computed>",
      "ranges": [
        {
          "startOffset": 8782,
          "endOffset": 8860,
          "count": 0
        }
      ],
      "isBlockCoverage": false
    },
    {
      "functionName": "AggregationCursor._transformForAsyncIterator",
      "ranges": [
        {
          "startOffset": 8941,
          "endOffset": 9085,
          "count": 0
        }
      ],
      "isBlockCoverage": false
    },
    {
      "functionName": "AggregationCursor.transformNull",
      "ranges": [
        {
          "startOffset": 9151,
          "endOffset": 9280,
          "count": 0
        }
      ],
      "isBlockCoverage": false
    },
    {
      "functionName": "_transformForAsyncIterator",
      "ranges": [
        {
          "startOffset": 9302,
          "endOffset": 9415,
          "count": 0
        }
      ],
      "isBlockCoverage": false
    },
    {
      "functionName": "AggregationCursor.addCursorFlag",
      "ranges": [
        {
          "startOffset": 9786,
          "endOffset": 9935,
          "count": 0
        }
      ],
      "isBlockCoverage": false
    },
    {
      "functionName": "_waitForCursor",
      "ranges": [
        {
          "startOffset": 9957,
          "endOffset": 10084,
          "count": 0
        }
      ],
      "isBlockCoverage": false
    },
    {
      "functionName": "_next",
      "ranges": [
        {
          "startOffset": 10241,
          "endOffset": 10965,
          "count": 0
        }
      ],
      "isBlockCoverage": false
    }
  ]
}