{
  "scriptId": "423",
  "url": "file:///C:/Users/AGX/AppData/Local/deno/npm/registry.npmjs.org/date-fns/4.1.0/differenceInWeeks.js",
  "functions": [
    {
      "functionName": "",
      "ranges": [
        {
          "startOffset": 0,
          "endOffset": 1805,
          "count": 1
        }
      ],
      "isBlockCoverage": true
    },
    {
      "functionName": "differenceInWeeks",
      "ranges": [
        {
          "startOffset": 1540,
          "endOffset": 1732,
          "count": 0
        }
      ],
      "isBlockCoverage": false
    }
  ]
}